{"code":"8976","name":"大和証券オフィス投資法人","market":"REIT・ベンチャーファンド・カントリーファンド・インフラファンド","sector":"-","fund":null,"prices":[],"short":{"series":[{"d":"2025-03-31","r":0.78,"i":1},{"d":"2025-04-04","r":0.8,"i":1},{"d":"2025-04-07","r":0.79,"i":1},{"d":"2025-04-08","r":0.8,"i":1},{"d":"2025-06-11","r":0.92,"i":1},{"d":"2025-07-17","r":1.01,"i":1},{"d":"2025-08-27","r":1.1,"i":1},{"d":"2025-08-29","r":1.09,"i":1},{"d":"2025-09-01","r":1.1,"i":1},{"d":"2025-09-03","r":1.09,"i":1},{"d":"2025-09-04","r":1.1,"i":1},{"d":"2025-09-12","r":1.04,"i":1},{"d":"2025-09-24","r":0.82,"i":1}],"inst":[{"institution":"みずほ証券株式会社","ratio":0.82,"shares":7774,"date":"2025-09-24","chg":-2104}]},"hits":[],"tags":[],"cost":{"agg":null,"rows":[],"close":null}}